Metadata-Version: 1.1
Name: quasi
Version: 0.1.1
Summary: Simple request wrapper
Home-page: https://gitlab.com/olymk2/quasi
Author: Oliver Marks
Author-email: oly@digitaloctave.com
License:                     GNU GENERAL PUBLIC LICENSE
